mave/loc.py
mave/trainers.py
mave/location.py
mave/get_weather.py
mave/dataset.py
mave/__init__.py
mave/core.py
mave/estimators.py
mave/visualize.py
mave/comparer.py
mave/holidays.py
mave/weather.py
mave/config/default.cfg
mave/data/ex4.csv
mave/data/clean_USA_CA_Oakland.Intl.AP.724930_TMY3.epw.csv
mave/data/ex1.csv
mave/data/clean_tmy.csv.csv
mave/data/weather_test.csv
mave/data/ex7.csv
mave/data/ex8.csv
mave/data/ex3.csv
mave/data/ex5.csv
mave/data/clean_tmy.csv
mave/data/ex2.csv
mave/data/epwurl.csv
mave/data/ex6.csv
mave-0.0.42.dist-info/top_level.txt
mave-0.0.42.dist-info/DESCRIPTION.rst
mave-0.0.42.dist-info/metadata.json
mave-0.0.42.dist-info/RECORD
mave-0.0.42.dist-info/WHEEL
mave-0.0.42.dist-info/METADATA
mave-0.0.42.dist-info/pbr.json
mave-0.0.42.data/scripts/mave
