Metadata-Version: 2.0
Name: mave
Version: 0.0.42
Summary: Package for Measurement and Verification
Home-page: https://github.com/centerforthebuiltenvironment/mave
Author: Paul Raftery
Author-email: praftery@berkeley.edu
License: GPLv3
Keywords: m&v measurement verification energy modeling
Platform: UNKNOWN
Classifier: Development Status :: 4 - Beta
Classifier: Intended Audience :: Education
Classifier: Intended Audience :: End Users/Desktop
Classifier: Intended Audience :: Science/Research
Classifier: Operating System :: OS Independent
Classifier: Topic :: Scientific/Engineering :: Information Analysis
Classifier: License :: OSI Approved :: GNU General Public License v2 or later (GPLv2+)
Classifier: Programming Language :: Python 
Classifier: Programming Language :: Python :: 2.7
Requires-Dist: numpy (>=1.9.0)
Requires-Dist: python-dateutil (>=2.4)
Requires-Dist: scikit-learn (>=0.16.1)
Requires-Dist: scipy (>=0.15.0)
Provides-Extra: dev
Requires-Dist: check-manifest; extra == 'dev'
Provides-Extra: test
Requires-Dist: coverage; extra == 'test'
